mw2fcitx/__init__.py
mw2fcitx/build_dict.py
mw2fcitx/const.py
mw2fcitx/dictgen/__init__.py
mw2fcitx/dictgen/pinyin.py
mw2fcitx/dictgen/rime.py
mw2fcitx/exporters/__init__.py
mw2fcitx/exporters/opencc.py
mw2fcitx/exporters/pypinyin.py
mw2fcitx/fetch.py
mw2fcitx/logging.py
mw2fcitx/main.py
mw2fcitx/pipeline.py
mw2fcitx/sample_config.py
mw2fcitx/sample_fixfile.json
mw2fcitx/tweaks/__init__.py
mw2fcitx/tweaks/moegirl.py
mw2fcitx/utils.py
mw2fcitx/version.py
mw2fcitx-0.24.2.dist-info/METADATA
mw2fcitx-0.24.2.dist-info/WHEEL
mw2fcitx-0.24.2.dist-info/entry_points.txt
mw2fcitx-0.24.2.dist-info/licenses/LICENSE
mw2fcitx-0.24.2.dist-info/RECORD
