Metadata-Version: 2.4
Name: mw2fcitx
Version: 0.24.2
Summary: Build fcitx5/RIME dictionaries from MediaWiki sites
License-Expression: MIT
License-File: LICENSE
Keywords: fcitx,dictionary
Author: Outvi V
Author-email: oss+pypi@outv.im>
Requires-Python: >=3.9
Classifier: Development Status :: 4 - Beta
Classifier: Environment :: Console
Classifier: Programming Language :: Python :: 3
Classifier: Programming Language :: Python :: 3.9
Classifier: Programming Language :: Python :: 3.10
Classifier: Programming Language :: Python :: 3.11
Classifier: Programming Language :: Python :: 3.12
Classifier: Programming Language :: Python :: 3.13
Classifier: Programming Language :: Python :: 3.14
Classifier: Topic :: Software Development :: Libraries :: Python Modules
Classifier: Topic :: Text Processing
Classifier: Topic :: Utilities
Provides-Extra: opencc
Requires-Dist: OpenCC (>=1.1.9,<2.0.0) ; extra == "opencc"
Requires-Dist: pypinyin (>=0.54.0,<0.55.0)
Requires-Dist: pyyaml (>=6.0.2,<7.0.0)
Requires-Dist: requests (>=2.32.4,<3.0.0)
Project-URL: Discussions, https://github.com/outloudvi/mw2fcitx/discussions
Project-URL: Issue Tracker, https://github.com/outloudvi/mw2fcitx/issues
Project-URL: Repository, https://github.com/outloudvi/mw2fcitx
